Workbook
Name Slicer_Month: #N/A
Name Slicer_Product: #N/A
Name Slicer_Region: #N/A

Sheet Product_Sheet
A2: Row Labels | B2: Sum of Sales
A3: Product A | B3: 643361
A4: Product B | B4: 866795
A5: Product C | B5: 1003131
A6: Grand Total | B6: 2513287

Sheet Region_Sheet
A3: Row Labels | B3: Count of Product
A4: East | B4: 12
A5: North | B5: 10
A6: South | B6: 14
A7: West | B7: 14
A8: Grand Total | B8: 50

Sheet Sales_Data
A1: Month | B1: Region | C1: Product | D1: Sales | E1: Cost | F1: Profit | G1: Sales Category
A2: Jun | B2: North | C2: Product C | D2: 78295 | E2: 34783 | F2: 43512 | G2: =IF(Table2[[#This Row],[Sales]]>60000,"High",IF(Table2[[#This Row],[Sales]]>=40000,"Medium","Low")) -> High
A3: Apr | B3: South | C3: Product A | D3: 77066 | E3: 34986 | F3: 42080 | G3: =IF(Table2[[#This Row],[Sales]]>60000,"High",IF(Table2[[#This Row],[Sales]]>=40000,"Medium","Low")) -> High
A4: Apr | B4: South | C4: Product C | D4: 75864 | E4: 42894 | F4: 32970 | G4: =IF(Table2[[#This Row],[Sales]]>60000,"High",IF(Table2[[#This Row],[Sales]]>=40000,"Medium","Low")) -> High
A5: Jun | B5: North | C5: Product B | D5: 74760 | E5: 12985 | F5: 61775 | G5: =IF(Table2[[#This Row],[Sales]]>60000,"High",IF(Table2[[#This Row],[Sales]]>=40000,"Medium","Low")) -> High
A6: Mar | B6: East | C6: Product C | D6: 73153 | E6: 37204 | F6: 35949 | G6: =IF(Table2[[#This Row],[Sales]]>60000,"High",IF(Table2[[#This Row],[Sales]]>=40000,"Medium","Low")) -> High
A7: May | B7: West | C7: Product B | D7: 72868 | E7: 48623 | F7: 24245 | G7: =IF(Table2[[#This Row],[Sales]]>60000,"High",IF(Table2[[#This Row],[Sales]]>=40000,"Medium","Low")) -> High
A8: May | B8: North | C8: Product A | D8: 72491 | E8: 66087 | F8: 6404 | G8: =IF(Table2[[#This Row],[Sales]]>60000,"High",IF(Table2[[#This Row],[Sales]]>=40000,"Medium","Low")) -> High
A9: Apr | B9: West | C9: Product B | D9: 69694 | E9: 41468 | F9: 28226 | G9: =IF(Table2[[#This Row],[Sales]]>60000,"High",IF(Table2[[#This Row],[Sales]]>=40000,"Medium","Low")) -> High
A10: Apr | B10: East | C10: Product C | D10: 69464 | E10: 64465 | F10: 4999 | G10: =IF(Table2[[#This Row],[Sales]]>60000,"High",IF(Table2[[#This Row],[Sales]]>=40000,"Medium","Low")) -> High
A11: Mar | B11: East | C11: Product A | D11: 69048 | E11: 23614 | F11: 45434 | G11: =IF(Table2[[#This Row],[Sales]]>60000,"High",IF(Table2[[#This Row],[Sales]]>=40000,"Medium","Low")) -> High
A12: May | B12: South | C12: Product C | D12: 67393 | E12: 32125 | F12: 35268 | G12: =IF(Table2[[#This Row],[Sales]]>60000,"High",IF(Table2[[#This Row],[Sales]]>=40000,"Medium","Low")) -> High
A13: Jun | B13: West | C13: Product C | D13: 64771 | E13: 47288 | F13: 17483 | G13: =IF(Table2[[#This Row],[Sales]]>60000,"High",IF(Table2[[#This Row],[Sales]]>=40000,"Medium","Low")) -> High
... A51: Apr | B51: North | C51: Product B | D51: 20652 | E51: 15402 | F51: 5250 | G51: =IF(Table2[[#This Row],[Sales]]>60000,"High",IF(Table2[[#This Row],[Sales]]>=40000,"Medium","Low")) -> Low

Sheet Summary
A1: Metric | B1: Value
A2: Total Sales | B2: =SUM(Sales_Data!D3:D52) -> 2434992
A3: Total Profit | B3: =SUM(Sales_Data!F3:F52) -> 934593
A4: Profit Margin | B4: =B3/B2 -> 0.38381769
A5: Total Cost | B5: =SUM(Sales_Data!E2:E51) -> 1535182
A6: Cost Ratio | B6: =B5/B2 -> 0.63046696

Sheet Monthly _Sales_Trend
A1: Row Labels | B1: Sum of Sales | C1: 3 Month Moving Average | F1: Month | G1: Month Number | H1: Actual Sales | I1: Forecast Sales
A2: Jan | B2: 319618 | E2: Actual | F2: Jan | G2: 1 | H2: 319618
A3: Feb | B3: 278262 | F3: Feb | G3: 2 | H3: 278262
A4: Mar | B4: 412137 | C4: =AVERAGE(B2:B4) -> 336672.33 | F4: Mar | G4: 3 | H4: 412137
A5: Apr | B5: 544753 | C5: =AVERAGE(B3:B5) -> 411717.33 | F5: Apr | G5: 4 | H5: 544753
A6: May | B6: 554221 | C6: =AVERAGE(B4:B6) -> 503703.67 | F6: May | G6: 5 | H6: 554221
A7: Jun | B7: 404296 | C7: =AVERAGE(B5:B7) -> 501090 | F7: Jun | G7: 6 | H7: 404296
A8: Grand Total | B8: 2513287 | E8: FORECAST | F8: Jul | G8: 7 | I8: =_xlfn.FORECAST.LINEAR(G8,H2:H7,G2:G7) -> 557269.47
F9: Aug | G9: 8 | I9: =_xlfn.FORECAST.LINEAR(G9,H3:H8,G3:G8) -> 596394.6
F10: Sep | G10: 9 | I10: =_xlfn.FORECAST.LINEAR(G10,H4:H9,G4:G9) -> 472527
A20: Row Labels | B20: Sum of Sales | C20: 3 Month Moving Average
A21: Jan | B21: 319618
A22: Feb | B22: 278262
A23: Mar | B23: 412137 | C23: =AVERAGE(B21:B23) -> 336672.33
A24: Apr | B24: 544753 | C24: =AVERAGE(B22:B24) -> 411717.33
A25: May | B25: 554221 | C25: =AVERAGE(B23:B25) -> 503703.67
A26: Jun | B26: 404296 | C26: =AVERAGE(B24:B26) -> 501090
A42: Used a 3-month moving average to smooth sales fluctuations and identify the underlying trend for short-term planning.

Sheet Cost_vs_Sales
A3: Row Labels | B3: Sum of Cost | C3: Sum of Sales
A4: Product A | B4: 438046 | C4: 643361
A5: Product B | B5: 516662 | C5: 866795
A6: Product C | B6: 580474 | C6: 1003131
A7: Grand Total | B7: 1535182 | C7: 2513287

Sheet Monthly_Profit_Trend
A1: Row Labels | B1: Sum of Profit
A2: Jan | B2: 105824
A3: Feb | B3: 107824
A4: Mar | B4: 188625
A5: Apr | B5: 185395
A6: May | B6: 208737
A7: Jun | B7: 181700
A8: Grand Total | B8: 978105

Sheet Region_Profit_Analysis
A1: Row Labels | B1: Sum of Profit
A2: East | B2: 229856
A3: North | B3: 222985
A4: South | B4: 315559
A5: West | B5: 209705
A6: Grand Total | B6: 978105

Sheet Product_Performance
A3: Row Labels | B3: Sum of Sales | C3: Sum of Profit
A4: Product A | B4: 643361 | C4: 205315
A5: Product B | B5: 866795 | C5: 350133
A6: Product C | B6: 1003131 | C6: 422657
A7: Grand Total | B7: 2513287 | C7: 978105

Sheet Sales_Category_Distribution
A3: Row Labels | B3: Count of Sales Category
A4: High | B4: 15
A5: Low | B5: 15
A6: Medium | B6: 20
A7: Grand Total | B7: 50

Sheet Sales_Dashboard
B2: Total Sales | C2: Total Profit | D2: Avg Profit % | E2: Best Product | F2: Best Region
B3: =SUM(Table2[Sales]) -> 2513287 | C3: =SUM(Sales_Data!F:F) -> 978105 | D3: =C3/B3 -> 0.38917362 | E3: =INDEX(Product_Sheet!A2:A4, MATCH(MAX(Product_Sheet!B2:B4), Product_Sheet!B2:B4, 0)) -> Product B | F3: =INDEX(Region_Sheet!A2:A5, MATCH(MAX(Region_Sheet!B2:B5), Region_Sheet!B2:B5, 0)) -> East
